richtypes/__init__.py
richtypes/richdict.py
richtypes/richlist.py
richtypes-0.0.1.dist-info/LICENSE
richtypes-0.0.1.dist-info/METADATA
richtypes-0.0.1.dist-info/WHEEL
richtypes-0.0.1.dist-info/top_level.txt
richtypes-0.0.1.dist-info/RECORD
