Metadata-Version: 2.1
Name: richtypes
Version: 0.0.1
Summary: Enhanced python datatypes
Home-page: https://github.com/sarvesh4396/richtypes
Author: Sarvesh Kumar Dwivedi
Author-email: heysarvesh@pm.me
License: MIT
Keywords: richtypes,DATATYPES,ENHANCEMENT,LISTS,DICTIONARY,UTILITY
Classifier: Development Status :: 4 - Beta
Classifier: Intended Audience :: Developers
Classifier: License :: OSI Approved :: MIT License
Classifier: Topic :: Software Development :: User Interfaces
Classifier: Typing :: Typed
Classifier: Topic :: Utilities
Classifier: Programming Language :: Python :: 3.7
Classifier: Programming Language :: Python :: 3.8
Classifier: Programming Language :: Python :: 3.9
Requires-Python: >=3.7.0
License-File: LICENSE
Provides-Extra: dev
Requires-Dist: pytest ; extra == 'dev'
Requires-Dist: pytest-pep8 ; extra == 'dev'
Requires-Dist: pytest-cov ; extra == 'dev'
